calltracer/__init__.py
calltracer/module.py
call_tracer-1.2.2.dist-info/METADATA
call_tracer-1.2.2.dist-info/WHEEL
call_tracer-1.2.2.dist-info/top_level.txt
call_tracer-1.2.2.dist-info/RECORD
